road_collisions_uk/__init__.py
road_collisions_uk/download.py
road_collisions_uk/utils.py
road_collisions_uk/bin/__init__.py
road_collisions_uk/bin/load.py
road_collisions_uk/models/__init__.py
road_collisions_uk/models/casualty.py
road_collisions_uk/models/collision.py
road_collisions_uk/models/vehicle.py
road_collisions_uk-0.0.3.dist-info/METADATA
road_collisions_uk-0.0.3.dist-info/WHEEL
road_collisions_uk-0.0.3.dist-info/entry_points.txt
road_collisions_uk-0.0.3.dist-info/top_level.txt
road_collisions_uk-0.0.3.dist-info/RECORD
